retroPy/__init__.py
retroPy/retroPy.py
retropym-0.0.2.dist-info/METADATA
retropym-0.0.2.dist-info/WHEEL
retropym-0.0.2.dist-info/top_level.txt
retropym-0.0.2.dist-info/RECORD
